[
  {
    "cod": "CS9654844",
    "scoala": "ŞCOALA GIMNAZIALĂ NR.7 REŞIŢA",
    "materie": "Limba și literatura română",
    "nota_initiala": 8.6,
    "nota_finala": 9.1,
    "diferenta": 0.5
  },
  {
    "cod": "CS9753727",
    "scoala": "ȘCOALA GIMNAZIALĂ ROMUL LADEA ORAVIȚA",
    "materie": "Limba și literatura română",
    "nota_initiala": 9.2,
    "nota_finala": 9.3,
    "diferenta": 0.1
  },
  {
    "cod": "CS9322376",
    "scoala": "ȘCOALA PROFESIONALA BERZOVIA",
    "materie": "Limba și literatura română",
    "nota_initiala": 8.7,
    "nota_finala": 9,
    "diferenta": 0.3
  },
  {
    "cod": "CS9817466",
    "scoala": "ŞCOALA GIMNAZIALĂ GRUNI",
    "materie": "Limba și literatura română",
    "nota_initiala": 8.65,
    "nota_finala": 9.3,
    "diferenta": 0.65
  },
  {
    "cod": "CS9801503",
    "scoala": "COLEGIUL NAŢIONAL „TRAIAN LALESCU“ REŞIŢA",
    "materie": "Matematică",
    "nota_initiala": 9.1,
    "nota_finala": 9.15,
    "diferenta": 0.05
  },
  {
    "cod": "CS10362088",
    "scoala": "ŞCOALA GIMNAZIALĂ „MIHAI PEIA“ REŞIŢA",
    "materie": "Limba și literatura română",
    "nota_initiala": 8.8,
    "nota_finala": 8.8,
    "diferenta": 0
  },
  {
    "cod": "CS10917813",
    "scoala": "LICEUL DE ARTE „SABIN PĂUŢA“ REŞIŢA",
    "materie": "Limba și literatura română",
    "nota_initiala": 8.8,
    "nota_finala": 9.2,
    "diferenta": 0.4
  },
  {
    "cod": "CS9536918",
    "scoala": "ŞCOALA GIMNAZIALĂ NR.7 REŞIŢA",
    "materie": "Limba și literatura română",
    "nota_initiala": 8.75,
    "nota_finala": 9.2,
    "diferenta": 0.45
  },
  {
    "cod": "CS8928598",
    "scoala": "COLEGIUL NAŢIONAL „TRAIAN LALESCU“ REŞIŢA",
    "materie": "Limba și literatura română",
    "nota_initiala": 8.4,
    "nota_finala": 8.7,
    "diferenta": 0.3
  },
  {
    "cod": "CS8928598",
    "scoala": "COLEGIUL NAŢIONAL „TRAIAN LALESCU“ REŞIŢA",
    "materie": "Matematică",
    "nota_initiala": 8.95,
    "nota_finala": 9.4,
    "diferenta": 0.45
  },
  {
    "cod": "CS7942136",
    "scoala": "ŞCOALA GIMNAZIALĂ NR.7 REŞIŢA",
    "materie": "Limba și literatura română",
    "nota_initiala": 8.4,
    "nota_finala": 8.35,
    "diferenta": -0.05
  },
  {
    "cod": "CS8930781",
    "scoala": "COLEGIUL NAȚIONAL „DIACONOVICI TIETZ“ REŞIŢA",
    "materie": "Limba și literatura română",
    "nota_initiala": 7.9,
    "nota_finala": 7.85,
    "diferenta": -0.05
  },
  {
    "cod": "CS11150841",
    "scoala": "LICEUL TEORETIC TATA OANCEA BOCŞA",
    "materie": "Limba și literatura română",
    "nota_initiala": 8.2,
    "nota_finala": 8.8,
    "diferenta": 0.6
  },
  {
    "cod": "CS8932469",
    "scoala": "COLEGIUL NAŢIONAL „TRAIAN LALESCU“ REŞIŢA",
    "materie": "Limba și literatura română",
    "nota_initiala": 8.4,
    "nota_finala": 8.6,
    "diferenta": 0.2
  },
  {
    "cod": "CS8930537",
    "scoala": "ŞCOALA GIMNAZIALĂ ”MARIUS ȘANDRU” REŞIŢA",
    "materie": "Limba și literatura română",
    "nota_initiala": 8.1,
    "nota_finala": 8.4,
    "diferenta": 0.3
  },
  {
    "cod": "CS8938466",
    "scoala": "COLEGIUL NAȚIONAL „DIACONOVICI TIETZ“ REŞIŢA",
    "materie": "Limba și literatura română",
    "nota_initiala": 8.6,
    "nota_finala": 8.6,
    "diferenta": 0
  },
  {
    "cod": "CS8541731",
    "scoala": "ŞCOALA GIMNAZIALĂ MACIOVA",
    "materie": "Limba și literatura română",
    "nota_initiala": 8,
    "nota_finala": 8.3,
    "diferenta": 0.3
  },
  {
    "cod": "CS9792667",
    "scoala": "ŞCOALA GIMNAZIALĂ ”MARIUS ȘANDRU” REŞIŢA",
    "materie": "Limba și literatura română",
    "nota_initiala": 7.75,
    "nota_finala": 7.6,
    "diferenta": -0.15
  },
  {
    "cod": "CS9639636",
    "scoala": "LICEUL HERCULES BAILE HERCULANE",
    "materie": "Limba și literatura română",
    "nota_initiala": 8.45,
    "nota_finala": 9,
    "diferenta": 0.55
  },
  {
    "cod": "CS10389959",
    "scoala": "LICEUL HERCULES BAILE HERCULANE",
    "materie": "Limba și literatura română",
    "nota_initiala": 8.1,
    "nota_finala": 8.5,
    "diferenta": 0.4
  },
  {
    "cod": "CS9820328",
    "scoala": "COLEGIUL NAŢIONAL „TRAIAN LALESCU“ REŞIŢA",
    "materie": "Limba și literatura română",
    "nota_initiala": 8.4,
    "nota_finala": 8,
    "diferenta": -0.4
  },
  {
    "cod": "CS9783085",
    "scoala": "ŞCOALA GIMNAZIALĂ NR.8 REŞIŢA",
    "materie": "Matematică",
    "nota_initiala": 8.4,
    "nota_finala": 8.3,
    "diferenta": -0.1
  },
  {
    "cod": "CS10818412",
    "scoala": "ŞCOALA GIMNAZIALĂ CUPTOARE",
    "materie": "Limba și literatura română",
    "nota_initiala": 7.5,
    "nota_finala": 8.5,
    "diferenta": 1
  },
  {
    "cod": "CS9519279",
    "scoala": "LICEUL TEHNOLOGIC CLISURA DUNĂRII MOLDOVA NOUĂ",
    "materie": "Limba și literatura română",
    "nota_initiala": 8.3,
    "nota_finala": 8.8,
    "diferenta": 0.5
  },
  {
    "cod": "CS9640029",
    "scoala": "LICEUL HERCULES BAILE HERCULANE",
    "materie": "Limba și literatura română",
    "nota_initiala": 7.5,
    "nota_finala": 8.3,
    "diferenta": 0.8
  },
  {
    "cod": "CS9533790",
    "scoala": "ŞCOALA GIMNAZIALĂ NR.7 REŞIŢA",
    "materie": "Limba și literatura română",
    "nota_initiala": 8.2,
    "nota_finala": 8.8,
    "diferenta": 0.6
  },
  {
    "cod": "CS9533790",
    "scoala": "ŞCOALA GIMNAZIALĂ NR.7 REŞIŢA",
    "materie": "Matematică",
    "nota_initiala": 7.75,
    "nota_finala": 7.8,
    "diferenta": 0.05
  },
  {
    "cod": "CS10819148",
    "scoala": "ŞCOALA GIMNAZIALĂ CUPTOARE",
    "materie": "Limba și literatura română",
    "nota_initiala": 7.9,
    "nota_finala": 7.8,
    "diferenta": -0.1
  },
  {
    "cod": "CS9638628",
    "scoala": "LICEUL HERCULES BAILE HERCULANE",
    "materie": "Limba și literatura română",
    "nota_initiala": 8,
    "nota_finala": 8.4,
    "diferenta": 0.4
  },
  {
    "cod": "CS9320684",
    "scoala": "LICEUL TEORETIC TATA OANCEA BOCŞA",
    "materie": "Limba și literatura română",
    "nota_initiala": 7.65,
    "nota_finala": 8,
    "diferenta": 0.35
  },
  {
    "cod": "CS10389885",
    "scoala": "LICEUL HERCULES BAILE HERCULANE",
    "materie": "Limba și literatura română",
    "nota_initiala": 7.85,
    "nota_finala": 8,
    "diferenta": 0.15
  },
  {
    "cod": "CS9639365",
    "scoala": "LICEUL HERCULES BAILE HERCULANE",
    "materie": "Limba și literatura română",
    "nota_initiala": 8.45,
    "nota_finala": 8.7,
    "diferenta": 0.25
  },
  {
    "cod": "CS7942706",
    "scoala": "ŞCOALA GIMNAZIALĂ ”MARIUS ȘANDRU” REŞIŢA",
    "materie": "Limba și literatura română",
    "nota_initiala": 7.6,
    "nota_finala": 8,
    "diferenta": 0.4
  },
  {
    "cod": "CS7942706",
    "scoala": "ŞCOALA GIMNAZIALĂ ”MARIUS ȘANDRU” REŞIŢA",
    "materie": "Matematică",
    "nota_initiala": 8.25,
    "nota_finala": 8.15,
    "diferenta": -0.1
  },
  {
    "cod": "CS10917992",
    "scoala": "LICEUL DE ARTE „SABIN PĂUŢA“ REŞIŢA",
    "materie": "Limba și literatura română",
    "nota_initiala": 7.5,
    "nota_finala": 7.7,
    "diferenta": 0.2
  },
  {
    "cod": "CS9518905",
    "scoala": "LICEUL TEHNOLOGIC CLISURA DUNĂRII MOLDOVA NOUĂ",
    "materie": "Matematică",
    "nota_initiala": 6.8,
    "nota_finala": 6.8,
    "diferenta": 0
  },
  {
    "cod": "CS8825435",
    "scoala": "COLEGIUL NAŢIONAL TRAIAN DODA CARANSEBEŞ",
    "materie": "Limba și literatura română",
    "nota_initiala": 6.4,
    "nota_finala": 7.15,
    "diferenta": 0.75
  },
  {
    "cod": "CS9517196",
    "scoala": "LICEUL TEHNOLOGIC CLISURA DUNĂRII MOLDOVA NOUĂ",
    "materie": "Limba și literatura română",
    "nota_initiala": 7.55,
    "nota_finala": 7.1,
    "diferenta": -0.45
  },
  {
    "cod": "CS9131028",
    "scoala": "COLEGIUL NAŢIONAL TRAIAN DODA CARANSEBEŞ",
    "materie": "Limba și literatura română",
    "nota_initiala": 7.45,
    "nota_finala": 7.8,
    "diferenta": 0.35
  },
  {
    "cod": "CS9817370",
    "scoala": "ŞCOALA PROFESIONALĂ AGRICOLĂ CORNEREVA",
    "materie": "Limba și literatura română",
    "nota_initiala": 7.35,
    "nota_finala": 7.6,
    "diferenta": 0.25
  },
  {
    "cod": "CS9917754",
    "scoala": "LICEUL DE ARTE „SABIN PĂUŢA“ REŞIŢA",
    "materie": "Limba și literatura română",
    "nota_initiala": 6.6,
    "nota_finala": 7,
    "diferenta": 0.4
  },
  {
    "cod": "CS9140670",
    "scoala": "COLEGIUL NAŢIONAL TRAIAN DODA CARANSEBEŞ",
    "materie": "Matematică",
    "nota_initiala": 6.55,
    "nota_finala": 6.7,
    "diferenta": 0.15
  },
  {
    "cod": "CS9644220",
    "scoala": "LICEUL HERCULES BAILE HERCULANE",
    "materie": "Limba și literatura română",
    "nota_initiala": 8,
    "nota_finala": 8.1,
    "diferenta": 0.1
  },
  {
    "cod": "CS9816428",
    "scoala": "ŞCOALA PROFESIONALĂ AGRICOLĂ CORNEREVA",
    "materie": "Limba și literatura română",
    "nota_initiala": 6.7,
    "nota_finala": 7.1,
    "diferenta": 0.4
  },
  {
    "cod": "CS9533488",
    "scoala": "ŞCOALA GIMNAZIALĂ NR.7 REŞIŢA",
    "materie": "Matematică",
    "nota_initiala": 6.45,
    "nota_finala": 6.4,
    "diferenta": -0.05
  },
  {
    "cod": "CS9995136",
    "scoala": "COLEGIUL NAŢIONAL C.D. LOGA CARANSEBEŞ",
    "materie": "Limba și literatura română",
    "nota_initiala": 7.8,
    "nota_finala": 8.1,
    "diferenta": 0.3
  },
  {
    "cod": "CS9537317",
    "scoala": "ŞCOALA GIMNAZIALĂ NR.7 REŞIŢA",
    "materie": "Limba și literatura română",
    "nota_initiala": 7.65,
    "nota_finala": 7.6,
    "diferenta": -0.05
  },
  {
    "cod": "CS10321575",
    "scoala": "ŞCOALA GIMNAZIALĂ NR.1 OŢELU ROŞU",
    "materie": "Limba și literatura română",
    "nota_initiala": 6.45,
    "nota_finala": 6.9,
    "diferenta": 0.45
  },
  {
    "cod": "CS10921937",
    "scoala": "ŞCOALA GIMNAZIALĂ ARMENIŞ",
    "materie": "Matematică",
    "nota_initiala": 5.9,
    "nota_finala": 5.85,
    "diferenta": -0.05
  },
  {
    "cod": "CS9517807",
    "scoala": "LICEUL TEHNOLOGIC CLISURA DUNĂRII MOLDOVA NOUĂ",
    "materie": "Limba și literatura română",
    "nota_initiala": 7.1,
    "nota_finala": 7.2,
    "diferenta": 0.1
  },
  {
    "cod": "CS9817251",
    "scoala": "ŞCOALA PROFESIONALĂ AGRICOLĂ CORNEREVA",
    "materie": "Limba și literatura română",
    "nota_initiala": 6.75,
    "nota_finala": 7.05,
    "diferenta": 0.3
  },
  {
    "cod": "CS9330294",
    "scoala": "LICEUL TEHNOLOGIC CLISURA DUNĂRII MOLDOVA NOUĂ",
    "materie": "Limba și literatura română",
    "nota_initiala": 7.15,
    "nota_finala": 7.65,
    "diferenta": 0.5
  },
  {
    "cod": "CS12173661",
    "scoala": "ŞCOALA GIMNAZIALĂ SICHEVIŢA",
    "materie": "Limba și literatura română",
    "nota_initiala": 7.6,
    "nota_finala": 7.6,
    "diferenta": 0
  },
  {
    "cod": "CS12173661",
    "scoala": "ŞCOALA GIMNAZIALĂ SICHEVIŢA",
    "materie": "Matematică",
    "nota_initiala": 6.9,
    "nota_finala": 6.9,
    "diferenta": 0
  },
  {
    "cod": "CS9636289",
    "scoala": "LICEUL HERCULES BAILE HERCULANE",
    "materie": "Limba și literatura română",
    "nota_initiala": 7.45,
    "nota_finala": 7.8,
    "diferenta": 0.35
  },
  {
    "cod": "CS10001456",
    "scoala": "COLEGIUL NAŢIONAL C.D. LOGA CARANSEBEŞ",
    "materie": "Limba și literatura română",
    "nota_initiala": 7.9,
    "nota_finala": 7.55,
    "diferenta": -0.35
  },
  {
    "cod": "CS10001456",
    "scoala": "COLEGIUL NAŢIONAL C.D. LOGA CARANSEBEŞ",
    "materie": "Matematică",
    "nota_initiala": 6.95,
    "nota_finala": 6.85,
    "diferenta": -0.1
  },
  {
    "cod": "CS9801652",
    "scoala": "COLEGIUL NAŢIONAL „TRAIAN LALESCU“ REŞIŢA",
    "materie": "Limba și literatura română",
    "nota_initiala": 6.65,
    "nota_finala": 6.35,
    "diferenta": -0.3
  },
  {
    "cod": "CS9998547",
    "scoala": "COLEGIUL NAŢIONAL C.D. LOGA CARANSEBEŞ",
    "materie": "Limba și literatura română",
    "nota_initiala": 6.45,
    "nota_finala": 7.1,
    "diferenta": 0.65
  },
  {
    "cod": "CS9851203",
    "scoala": "COLEGIUL NAŢIONAL C.D. LOGA CARANSEBEŞ",
    "materie": "Limba și literatura română",
    "nota_initiala": 7.4,
    "nota_finala": 7.7,
    "diferenta": 0.3
  },
  {
    "cod": "CS9781895",
    "scoala": "COLEGIUL NAȚIONAL „DIACONOVICI TIETZ“ REŞIŢA",
    "materie": "Limba și literatura română",
    "nota_initiala": 7.4,
    "nota_finala": 8,
    "diferenta": 0.6
  },
  {
    "cod": "CS9535411",
    "scoala": "ŞCOALA GIMNAZIALĂ NR.7 REŞIŢA",
    "materie": "Limba și literatura română",
    "nota_initiala": 6.6,
    "nota_finala": 6.8,
    "diferenta": 0.2
  },
  {
    "cod": "CS9330419",
    "scoala": "LICEUL TEHNOLOGIC CLISURA DUNĂRII MOLDOVA NOUĂ",
    "materie": "Limba și literatura română",
    "nota_initiala": 6.75,
    "nota_finala": 6.7,
    "diferenta": -0.05
  },
  {
    "cod": "CS9637730",
    "scoala": "LICEUL HERCULES BAILE HERCULANE",
    "materie": "Limba și literatura română",
    "nota_initiala": 6.65,
    "nota_finala": 6.5,
    "diferenta": -0.15
  },
  {
    "cod": "CS10389628",
    "scoala": "LICEUL HERCULES BAILE HERCULANE",
    "materie": "Limba și literatura română",
    "nota_initiala": 5.8,
    "nota_finala": 6.4,
    "diferenta": 0.6
  },
  {
    "cod": "CS10001345",
    "scoala": "COLEGIUL NAŢIONAL C.D. LOGA CARANSEBEŞ",
    "materie": "Limba și literatura română",
    "nota_initiala": 6.2,
    "nota_finala": 6.65,
    "diferenta": 0.45
  },
  {
    "cod": "CS9654899",
    "scoala": "COLEGIUL NAŢIONAL „MIRCEA ELIADE“ REŞIŢA",
    "materie": "Limba și literatura română",
    "nota_initiala": 6.55,
    "nota_finala": 7,
    "diferenta": 0.45
  },
  {
    "cod": "CS9730724",
    "scoala": "ŞCOALA GIMNAZIALĂ SICHEVIŢA",
    "materie": "Limba și literatura română",
    "nota_initiala": 6.7,
    "nota_finala": 7.1,
    "diferenta": 0.4
  },
  {
    "cod": "CS9730724",
    "scoala": "ŞCOALA GIMNAZIALĂ SICHEVIŢA",
    "materie": "Matematică",
    "nota_initiala": 6.2,
    "nota_finala": 6.3,
    "diferenta": 0.1
  },
  {
    "cod": "CS9884103",
    "scoala": "ŞCOALA GIMNAZIALĂ IABLANIŢA",
    "materie": "Matematică",
    "nota_initiala": 6.25,
    "nota_finala": 6.2,
    "diferenta": -0.05
  },
  {
    "cod": "CS8345683",
    "scoala": "LICEUL TEHNOLOGIC DECEBAL CARANSEBEŞ",
    "materie": "Limba și literatura română",
    "nota_initiala": 5.4,
    "nota_finala": 5.8,
    "diferenta": 0.4
  },
  {
    "cod": "CS10322043",
    "scoala": "ŞCOALA GIMNAZIALĂ NR.1 OŢELU ROŞU",
    "materie": "Limba și literatura română",
    "nota_initiala": 5,
    "nota_finala": 5.6,
    "diferenta": 0.6
  },
  {
    "cod": "CS10627209",
    "scoala": "ŞCOALA GIMNAZIALĂ NR.1 BOCŞA",
    "materie": "Matematică",
    "nota_initiala": 6.65,
    "nota_finala": 6.65,
    "diferenta": 0
  },
  {
    "cod": "CS9959125",
    "scoala": "LICEUL TEHNOLOGIC „NICOLAE STOICA DE HAŢEG“ MEHADIA",
    "materie": "Limba și literatura română",
    "nota_initiala": 6.55,
    "nota_finala": 5.9,
    "diferenta": -0.65
  },
  {
    "cod": "CS11094267",
    "scoala": "ŞCOALA GIMNAZIALĂ SLATINA-TIMIŞ",
    "materie": "Matematică",
    "nota_initiala": 4.75,
    "nota_finala": 4.7,
    "diferenta": -0.05
  },
  {
    "cod": "CS9809477",
    "scoala": "ŞCOALA GIMNAZIALĂ „ALEXANDRU MOISI“ MOLDOVA NOUĂ",
    "materie": "Matematică",
    "nota_initiala": 4.5,
    "nota_finala": 4.25,
    "diferenta": -0.25
  },
  {
    "cod": "CS8816068",
    "scoala": "COLEGIUL NAŢIONAL TRAIAN DODA CARANSEBEŞ",
    "materie": "Limba și literatura română",
    "nota_initiala": 6.8,
    "nota_finala": 6.8,
    "diferenta": 0
  },
  {
    "cod": "CS8816068",
    "scoala": "COLEGIUL NAŢIONAL TRAIAN DODA CARANSEBEŞ",
    "materie": "Matematică",
    "nota_initiala": 5.95,
    "nota_finala": 5.6,
    "diferenta": -0.35
  },
  {
    "cod": "CS10311734",
    "scoala": "ŞCOALA GIMNAZIALĂ NR.1 OŢELU ROŞU",
    "materie": "Limba și literatura română",
    "nota_initiala": 5,
    "nota_finala": 5.5,
    "diferenta": 0.5
  },
  {
    "cod": "CS9943043",
    "scoala": "LICEUL TEHNOLOGIC „SF.DIMITRIE“ TEREGOVA",
    "materie": "Limba și literatura română",
    "nota_initiala": 6.55,
    "nota_finala": 7.55,
    "diferenta": 1
  },
  {
    "cod": "CS9139763",
    "scoala": "COLEGIUL NAŢIONAL TRAIAN DODA CARANSEBEŞ",
    "materie": "Limba și literatura română",
    "nota_initiala": 6.05,
    "nota_finala": 6.5,
    "diferenta": 0.45
  },
  {
    "cod": "CS13896000",
    "scoala": "ŞCOALA GIMNAZIALĂ DOMAŞNEA",
    "materie": "Limba și literatura română",
    "nota_initiala": 6.7,
    "nota_finala": 7.1,
    "diferenta": 0.4
  },
  {
    "cod": "CS9533544",
    "scoala": "LICEUL TEHNOLOGIC CLISURA DUNĂRII MOLDOVA NOUĂ",
    "materie": "Limba și literatura română",
    "nota_initiala": 5.15,
    "nota_finala": 5,
    "diferenta": -0.15
  },
  {
    "cod": "CS9783569",
    "scoala": "LICEUL DE ARTE „SABIN PĂUŢA“ REŞIŢA",
    "materie": "Limba și literatura română",
    "nota_initiala": 5.6,
    "nota_finala": 5.5,
    "diferenta": -0.1
  },
  {
    "cod": "CS9783569",
    "scoala": "LICEUL DE ARTE „SABIN PĂUŢA“ REŞIŢA",
    "materie": "Matematică",
    "nota_initiala": 6.05,
    "nota_finala": 6.05,
    "diferenta": 0
  },
  {
    "cod": "CS9819544",
    "scoala": "ŞCOALA PROFESIONALĂ AGRICOLĂ CORNEREVA",
    "materie": "Limba și literatura română",
    "nota_initiala": 4.8,
    "nota_finala": 4.8,
    "diferenta": 0
  },
  {
    "cod": "CS9785747",
    "scoala": "ȘCOALA GIMNAZIALĂ ROMUL LADEA ORAVIȚA",
    "materie": "Limba și literatura română",
    "nota_initiala": 5.85,
    "nota_finala": 5.8,
    "diferenta": -0.05
  },
  {
    "cod": "CS9785747",
    "scoala": "ȘCOALA GIMNAZIALĂ ROMUL LADEA ORAVIȚA",
    "materie": "Matematică",
    "nota_initiala": 5.7,
    "nota_finala": 5.55,
    "diferenta": -0.15
  },
  {
    "cod": "CS8816991",
    "scoala": "COLEGIUL NAŢIONAL TRAIAN DODA CARANSEBEŞ",
    "materie": "Limba și literatura română",
    "nota_initiala": 6.35,
    "nota_finala": 6.4,
    "diferenta": 0.05
  },
  {
    "cod": "CS9913971",
    "scoala": "ŞCOALA GIMNAZIALĂ NR.1 CELNIC",
    "materie": "Matematică",
    "nota_initiala": 4.6,
    "nota_finala": 4.5,
    "diferenta": -0.1
  },
  {
    "cod": "CS8609822",
    "scoala": "ŞCOALA GIMNAZIALĂ COPĂCELE",
    "materie": "Limba și literatura română",
    "nota_initiala": 6.5,
    "nota_finala": 6.2,
    "diferenta": -0.3
  },
  {
    "cod": "CS8609822",
    "scoala": "ŞCOALA GIMNAZIALĂ COPĂCELE",
    "materie": "Matematică",
    "nota_initiala": 5.4,
    "nota_finala": 4.85,
    "diferenta": -0.55
  },
  {
    "cod": "CS9759840",
    "scoala": "LICEUL „MATHIAS HAMMER“ ANINA",
    "materie": "Matematică",
    "nota_initiala": 4.9,
    "nota_finala": 4.9,
    "diferenta": 0
  },
  {
    "cod": "CS10307260",
    "scoala": "ŞCOALA GIMNAZIALĂ NR.3 OŢELU ROŞU",
    "materie": "Matematică",
    "nota_initiala": 4.4,
    "nota_finala": 4.4,
    "diferenta": 0
  },
  {
    "cod": "CS10573740",
    "scoala": "ŞCOALA GIMNAZIALĂ „PAVEL BORDAN“ GRĂDINARI",
    "materie": "Limba și literatura română",
    "nota_initiala": 5.05,
    "nota_finala": 5.5,
    "diferenta": 0.45
  },
  {
    "cod": "CS10573740",
    "scoala": "ŞCOALA GIMNAZIALĂ „PAVEL BORDAN“ GRĂDINARI",
    "materie": "Matematică",
    "nota_initiala": 4.9,
    "nota_finala": 4.9,
    "diferenta": 0
  },
  {
    "cod": "CS8928189",
    "scoala": "COLEGIUL NAȚIONAL „DIACONOVICI TIETZ“ REŞIŢA",
    "materie": "Limba și literatura română",
    "nota_initiala": 3.6,
    "nota_finala": 3.2,
    "diferenta": -0.4
  },
  {
    "cod": "CS9676399",
    "scoala": "COLEGIUL NAŢIONAL C.D. LOGA CARANSEBEŞ",
    "materie": "Matematică",
    "nota_initiala": 4.65,
    "nota_finala": 4.6,
    "diferenta": -0.05
  },
  {
    "cod": "CS9633667",
    "scoala": "ŞCOALA GIMNAZIALĂ „ŞTEFAN VELOVAN“ RUSCA MONTANĂ",
    "materie": "Matematică",
    "nota_initiala": 3.85,
    "nota_finala": 3.7,
    "diferenta": -0.15
  },
  {
    "cod": "CS9552089",
    "scoala": "ŞCOALA GIMNAZIALĂ „ALEXANDRU MOISI“ MOLDOVA NOUĂ",
    "materie": "Limba și literatura română",
    "nota_initiala": 6.75,
    "nota_finala": 6.8,
    "diferenta": 0.05
  },
  {
    "cod": "CS9552089",
    "scoala": "ŞCOALA GIMNAZIALĂ „ALEXANDRU MOISI“ MOLDOVA NOUĂ",
    "materie": "Matematică",
    "nota_initiala": 3.2,
    "nota_finala": 3.2,
    "diferenta": 0
  },
  {
    "cod": "CS8925916",
    "scoala": "COLEGIUL NAȚIONAL „DIACONOVICI TIETZ“ REŞIŢA",
    "materie": "Limba și literatura română",
    "nota_initiala": 5.45,
    "nota_finala": 5.4,
    "diferenta": -0.05
  },
  {
    "cod": "CS8823141",
    "scoala": "COLEGIUL NAŢIONAL TRAIAN DODA CARANSEBEŞ",
    "materie": "Limba și literatura română",
    "nota_initiala": 3.4,
    "nota_finala": 3.3,
    "diferenta": -0.1
  },
  {
    "cod": "CS9531124",
    "scoala": "ŞCOALA GIMNAZIALĂ NR.7 REŞIŢA",
    "materie": "Limba și literatura română",
    "nota_initiala": 3.25,
    "nota_finala": 3.5,
    "diferenta": 0.25
  },
  {
    "cod": "CS9546200",
    "scoala": "ŞCOALA GIMNAZIALĂ NR.7 REŞIŢA",
    "materie": "Limba și literatura română",
    "nota_initiala": 4.4,
    "nota_finala": 5,
    "diferenta": 0.6
  },
  {
    "cod": "CS9546200",
    "scoala": "ŞCOALA GIMNAZIALĂ NR.7 REŞIŢA",
    "materie": "Matematică",
    "nota_initiala": 4.7,
    "nota_finala": 4.7,
    "diferenta": 0
  },
  {
    "cod": "CS9141891",
    "scoala": "COLEGIUL NAŢIONAL TRAIAN DODA CARANSEBEŞ",
    "materie": "Limba și literatura română",
    "nota_initiala": 4.4,
    "nota_finala": 4.3,
    "diferenta": -0.1
  },
  {
    "cod": "CS9527187",
    "scoala": "ŞCOALA GIMNAZIALĂ BERZASCA",
    "materie": "Limba și literatura română",
    "nota_initiala": 2.7,
    "nota_finala": 2.85,
    "diferenta": 0.15
  },
  {
    "cod": "CS12140975",
    "scoala": "ŞCOALA GIMNAZIALĂ ZĂGUJENI",
    "materie": "Limba și literatura română",
    "nota_initiala": 5.35,
    "nota_finala": 5.3,
    "diferenta": -0.05
  },
  {
    "cod": "CS11134088",
    "scoala": "COLEGIUL NAŢIONAL „TRAIAN LALESCU“ REŞIŢA",
    "materie": "Matematică",
    "nota_initiala": 4.5,
    "nota_finala": 4.5,
    "diferenta": 0
  },
  {
    "cod": "CS9320247",
    "scoala": "LICEUL TEORETIC TATA OANCEA BOCŞA",
    "materie": "Limba și literatura română",
    "nota_initiala": 4,
    "nota_finala": 4.5,
    "diferenta": 0.5
  },
  {
    "cod": "CS9476155",
    "scoala": "ŞCOALA GIMNAZIALĂ BERZASCA",
    "materie": "Matematică",
    "nota_initiala": 4.4,
    "nota_finala": 4.3,
    "diferenta": -0.1
  },
  {
    "cod": "CS9736736",
    "scoala": "ŞCOALA GIMNAZIALĂ „PETRU OALLDE“ FOROTIC",
    "materie": "Matematică",
    "nota_initiala": 2.75,
    "nota_finala": 2.7,
    "diferenta": -0.05
  },
  {
    "cod": "CS9322278",
    "scoala": "ŞCOALA GIMNAZIALĂ „AUREL PEIA“ EZERIŞ",
    "materie": "Limba și literatura română",
    "nota_initiala": 5,
    "nota_finala": 5,
    "diferenta": 0
  },
  {
    "cod": "CS9154690",
    "scoala": "COLEGIUL NAŢIONAL „MIRCEA ELIADE“ REŞIŢA",
    "materie": "Matematică",
    "nota_initiala": 4.2,
    "nota_finala": 4.2,
    "diferenta": 0
  },
  {
    "cod": "CS10053156",
    "scoala": "ŞCOALA GIMNAZIALĂ LUPAC",
    "materie": "Limba și literatura română",
    "nota_initiala": 4.4,
    "nota_finala": 4,
    "diferenta": -0.4
  },
  {
    "cod": "CS9914646",
    "scoala": "ŞCOALA GIMNAZIALĂ NR.2 STEIERDORF",
    "materie": "Limba și literatura română",
    "nota_initiala": 4,
    "nota_finala": 4,
    "diferenta": 0
  },
  {
    "cod": "CS9900385",
    "scoala": "ȘCOALA GIMNAZIALĂ ROMUL LADEA ORAVIȚA",
    "materie": "Limba și literatura română",
    "nota_initiala": 3.6,
    "nota_finala": 3.5,
    "diferenta": -0.1
  },
  {
    "cod": "CS9900385",
    "scoala": "ȘCOALA GIMNAZIALĂ ROMUL LADEA ORAVIȚA",
    "materie": "Matematică",
    "nota_initiala": 5.7,
    "nota_finala": 5.7,
    "diferenta": 0
  },
  {
    "cod": "CS10923326",
    "scoala": "COLEGIUL NAŢIONAL „MIRCEA ELIADE“ REŞIŢA",
    "materie": "Limba și literatura română",
    "nota_initiala": 5,
    "nota_finala": 5,
    "diferenta": 0
  },
  {
    "cod": "CS13694164",
    "scoala": "COLEGIUL NAŢIONAL C.D. LOGA CARANSEBEŞ",
    "materie": "Limba și literatura română",
    "nota_initiala": 4.3,
    "nota_finala": 4.1,
    "diferenta": -0.2
  },
  {
    "cod": "CS9873667",
    "scoala": "LICEUL DE ARTE „SABIN PĂUŢA“ REŞIŢA",
    "materie": "Limba și literatura română",
    "nota_initiala": 3.45,
    "nota_finala": 3.1,
    "diferenta": -0.35
  },
  {
    "cod": "CS9954249",
    "scoala": "ŞCOALA GIMNAZIALĂ NR.2 STEIERDORF",
    "materie": "Matematică",
    "nota_initiala": 4.25,
    "nota_finala": 4,
    "diferenta": -0.25
  },
  {
    "cod": "CS9573581",
    "scoala": "ŞCOALA GIMNAZIALĂ NR.7 REŞIŢA",
    "materie": "Limba și literatura română",
    "nota_initiala": 4,
    "nota_finala": 4.15,
    "diferenta": 0.15
  },
  {
    "cod": "CS10289281",
    "scoala": "LICEUL „MATHIAS HAMMER“ ANINA",
    "materie": "Matematică",
    "nota_initiala": 4.7,
    "nota_finala": 4.7,
    "diferenta": 0
  },
  {
    "cod": "CS9818105",
    "scoala": "ŞCOALA GIMNAZIALĂ GRUNI",
    "materie": "Limba și literatura română",
    "nota_initiala": 3.3,
    "nota_finala": 3.3,
    "diferenta": 0
  },
  {
    "cod": "CS9898871",
    "scoala": "COLEGIUL NAŢIONAL C.D. LOGA CARANSEBEŞ",
    "materie": "Limba și literatura română",
    "nota_initiala": 3.8,
    "nota_finala": 3.55,
    "diferenta": -0.25
  },
  {
    "cod": "CS9743655",
    "scoala": "ŞCOALA GIMNAZIALĂ „PETRU OALLDE“ FOROTIC",
    "materie": "Limba și literatura română",
    "nota_initiala": 4.9,
    "nota_finala": 5,
    "diferenta": 0.1
  },
  {
    "cod": "CS8282211",
    "scoala": "ŞCOALA GIMNAZIALĂ „TRANDAFIR COCÎRLĂ“ TURNU RUIENI",
    "materie": "Matematică",
    "nota_initiala": 2.2,
    "nota_finala": 2.2,
    "diferenta": 0
  },
  {
    "cod": "CS13699386",
    "scoala": "ŞCOALA GIMNAZIALĂ SLATINA-TIMIŞ",
    "materie": "Limba și literatura română",
    "nota_initiala": 3.75,
    "nota_finala": 3.9,
    "diferenta": 0.15
  },
  {
    "cod": "CS13699386",
    "scoala": "ŞCOALA GIMNAZIALĂ SLATINA-TIMIŞ",
    "materie": "Matematică",
    "nota_initiala": 4.5,
    "nota_finala": 4.55,
    "diferenta": 0.05
  },
  {
    "cod": "CS9151211",
    "scoala": "COLEGIUL NAŢIONAL „MIRCEA ELIADE“ REŞIŢA",
    "materie": "Limba și literatura română",
    "nota_initiala": 4.3,
    "nota_finala": 4.4,
    "diferenta": 0.1
  },
  {
    "cod": "CS9151211",
    "scoala": "COLEGIUL NAŢIONAL „MIRCEA ELIADE“ REŞIŢA",
    "materie": "Matematică",
    "nota_initiala": 4,
    "nota_finala": 4,
    "diferenta": 0
  },
  {
    "cod": "CS9899508",
    "scoala": "COLEGIUL NAŢIONAL C.D. LOGA CARANSEBEŞ",
    "materie": "Limba și literatura română",
    "nota_initiala": 5.15,
    "nota_finala": 5,
    "diferenta": -0.15
  },
  {
    "cod": "CS9899508",
    "scoala": "COLEGIUL NAŢIONAL C.D. LOGA CARANSEBEŞ",
    "materie": "Matematică",
    "nota_initiala": 3.35,
    "nota_finala": 3.3,
    "diferenta": -0.05
  },
  {
    "cod": "CS10924798",
    "scoala": "LICEUL TEORETIC „EFTIMIE MURGU“ BOZOVICI",
    "materie": "Limba și literatura română",
    "nota_initiala": 3.55,
    "nota_finala": 3.9,
    "diferenta": 0.35
  },
  {
    "cod": "CS9218333",
    "scoala": "COLEGIUL NAŢIONAL TRAIAN DODA CARANSEBEŞ",
    "materie": "Matematică",
    "nota_initiala": 4.25,
    "nota_finala": 4.25,
    "diferenta": 0
  },
  {
    "cod": "CS9487219",
    "scoala": "ŞCOALA GIMNAZIALĂ VERMEŞ",
    "materie": "Limba și literatura română",
    "nota_initiala": 3.05,
    "nota_finala": 4.3,
    "diferenta": 1.25
  },
  {
    "cod": "CS9518049",
    "scoala": "LICEUL TEHNOLOGIC CLISURA DUNĂRII MOLDOVA NOUĂ",
    "materie": "Limba și literatura română",
    "nota_initiala": 4.25,
    "nota_finala": 3.9,
    "diferenta": -0.35
  },
  {
    "cod": "CS9518049",
    "scoala": "LICEUL TEHNOLOGIC CLISURA DUNĂRII MOLDOVA NOUĂ",
    "materie": "Matematică",
    "nota_initiala": 4,
    "nota_finala": 4,
    "diferenta": 0
  },
  {
    "cod": "CS9987084",
    "scoala": "LICEUL TEORETIC BILINGV ROMÂNO-CROAT CARAŞOVA",
    "materie": "Limba și literatura română",
    "nota_initiala": 4.15,
    "nota_finala": 4.3,
    "diferenta": 0.15
  },
  {
    "cod": "CS10050741",
    "scoala": "ŞCOALA GIMNAZIALĂ IABLANIŢA",
    "materie": "Limba și literatura română",
    "nota_initiala": 3.8,
    "nota_finala": 4.05,
    "diferenta": 0.25
  },
  {
    "cod": "CS10050741",
    "scoala": "ŞCOALA GIMNAZIALĂ IABLANIŢA",
    "materie": "Matematică",
    "nota_initiala": 3.45,
    "nota_finala": 3.75,
    "diferenta": 0.3
  },
  {
    "cod": "CS9833837",
    "scoala": "COLEGIUL NAŢIONAL C.D. LOGA CARANSEBEŞ",
    "materie": "Limba și literatura română",
    "nota_initiala": 4.2,
    "nota_finala": 3.45,
    "diferenta": -0.75
  },
  {
    "cod": "CS9833837",
    "scoala": "COLEGIUL NAŢIONAL C.D. LOGA CARANSEBEŞ",
    "materie": "Matematică",
    "nota_initiala": 4.2,
    "nota_finala": 4.2,
    "diferenta": 0
  },
  {
    "cod": "CS10939112",
    "scoala": "LICEUL TEHNOLOGIC „IOSIF CORIOLAN BURACU“ PRIGOR",
    "materie": "Limba și literatura română",
    "nota_initiala": 4.15,
    "nota_finala": 4.05,
    "diferenta": -0.1
  },
  {
    "cod": "CS10922121",
    "scoala": "ŞCOALA GIMNAZIALĂ BĂNIA",
    "materie": "Limba și literatura română",
    "nota_initiala": 3.95,
    "nota_finala": 3.6,
    "diferenta": -0.35
  },
  {
    "cod": "CS10922121",
    "scoala": "ŞCOALA GIMNAZIALĂ BĂNIA",
    "materie": "Matematică",
    "nota_initiala": 3.7,
    "nota_finala": 3.7,
    "diferenta": 0
  },
  {
    "cod": "CS9219339",
    "scoala": "COLEGIUL NAŢIONAL TRAIAN DODA CARANSEBEŞ",
    "materie": "Limba și literatura română",
    "nota_initiala": 4.25,
    "nota_finala": 4.05,
    "diferenta": -0.2
  },
  {
    "cod": "CS9219339",
    "scoala": "COLEGIUL NAŢIONAL TRAIAN DODA CARANSEBEŞ",
    "materie": "Matematică",
    "nota_initiala": 3,
    "nota_finala": 3,
    "diferenta": 0
  },
  {
    "cod": "CS9590539",
    "scoala": "LICEUL TEHNOLOGIC „NICOLAE STOICA DE HAŢEG“ MEHADIA",
    "materie": "Limba și literatura română",
    "nota_initiala": 3,
    "nota_finala": 3,
    "diferenta": 0
  },
  {
    "cod": "CS9590539",
    "scoala": "LICEUL TEHNOLOGIC „NICOLAE STOICA DE HAŢEG“ MEHADIA",
    "materie": "Matematică",
    "nota_initiala": 2.2,
    "nota_finala": 2.1,
    "diferenta": -0.1
  },
  {
    "cod": "CS11044856",
    "scoala": "LICEUL TEHNOLOGIC „IOSIF CORIOLAN BURACU“ PRIGOR",
    "materie": "Limba și literatura română",
    "nota_initiala": 3,
    "nota_finala": 2.7,
    "diferenta": -0.3
  },
  {
    "cod": "CS11044856",
    "scoala": "LICEUL TEHNOLOGIC „IOSIF CORIOLAN BURACU“ PRIGOR",
    "materie": "Matematică",
    "nota_initiala": 2,
    "nota_finala": 2,
    "diferenta": 0
  }
]